slitherbox/arch.py
slitherbox/cat.py
slitherbox/echo.py
slitherbox/false.py
slitherbox/hostname.py
slitherbox/mkdir.py
slitherbox/mv.py
slitherbox/pwd.py
slitherbox/rm.py
slitherbox/sb_install.py
slitherbox/sb_list.py
slitherbox/sb_uninstall.py
slitherbox/sleep.py
slitherbox/slitherbox.py
slitherbox/touch.py
slitherbox/true.py
slitherbox/tty.py
slitherbox/uname.py
slitherbox/which.py
slitherbox/whoami.py
slitherbox-0.1.0.dist-info/LICENSE.txt
slitherbox-0.1.0.dist-info/METADATA
slitherbox-0.1.0.dist-info/WHEEL
slitherbox-0.1.0.dist-info/top_level.txt
slitherbox-0.1.0.dist-info/RECORD
