Metadata-Version: 2.1
Name: slitherbox
Version: 0.1.0
Summary: A drop-in pure-Python replacement for common shell utilities
Author-email: joshiemoore <jxm5210@g.rit.edu>
License: GNU GENERAL PUBLIC LICENSE
Project-URL: Homepage, https://github.com/joshiemoore/slitherbox
License-File: LICENSE.txt
